pytket/extensions/quantinuum/__init__.py
pytket/extensions/quantinuum/_metadata.py
pytket/extensions/quantinuum/py.typed
pytket/extensions/quantinuum/backends/__init__.py
pytket/extensions/quantinuum/backends/api_wrappers.py
pytket/extensions/quantinuum/backends/config.py
pytket/extensions/quantinuum/backends/data.py
pytket/extensions/quantinuum/backends/leakage_gadget.py
pytket/extensions/quantinuum/backends/quantinuum.py
pytket_quantinuum-0.57.0.dist-info/licenses/LICENSE
tests/integration/backend_test.py
tests/integration/local_emulator_multithreading_test.py
tests/integration/local_emulator_test.py
tests/unit/convert_test.py
tests/unit/data_test.py
tests/unit/leakage_detection_test.py
tests/unit/offline_backend_test.py
pytket_quantinuum-0.57.0.dist-info/METADATA
pytket_quantinuum-0.57.0.dist-info/WHEEL
pytket_quantinuum-0.57.0.dist-info/top_level.txt
pytket_quantinuum-0.57.0.dist-info/RECORD
