Metadata-Version: 2.4
Name: pytket-quantinuum
Version: 0.57.0
Summary: Extension for pytket, providing access to Quantinuum backends
Author-email: TKET development team <tket-support@quantinuum.com>
Maintainer-email: TKET development team <tket-support@quantinuum.com>
License:                                  Apache License
Project-URL: documentation, https://tket.quantinuum.com/extensions/pytket-quantinuum/index.html
Project-URL: source, https://github.com/Quantinuum/pytket-quantinuum
Project-URL: tracker, https://github.com/Quantinuum/pytket-quantinuum/issues
Classifier: Environment :: Console
Classifier: Programming Language :: Python :: 3.10
Classifier: Programming Language :: Python :: 3.11
Classifier: Programming Language :: Python :: 3.12
Classifier: Programming Language :: Python :: 3.13
Classifier: Operating System :: MacOS :: MacOS X
Classifier: Operating System :: POSIX :: Linux
Classifier: Operating System :: Microsoft :: Windows
Classifier: Intended Audience :: Developers
Classifier: Intended Audience :: Science/Research
Classifier: Topic :: Scientific/Engineering
Requires-Python: <4.0,>=3.10
License-File: LICENSE
Requires-Dist: pytket>=2.11.0
Requires-Dist: pytket-qir>=0.25.0
Requires-Dist: numpy>=1.26.4
Provides-Extra: pecos
Requires-Dist: pytket-pecos~=0.2.2; extra == "pecos"
Requires-Dist: quantum-pecos==0.7.0.dev4; extra == "pecos"
Requires-Dist: pytket-phir~=0.10.1; extra == "pecos"
Dynamic: license-file
